morgen_example_2/__init__.py
morgen_example_2/morgen_example_2.py
morgen_example_2-0.0.0.dist-info/LICENSE
morgen_example_2-0.0.0.dist-info/METADATA
morgen_example_2-0.0.0.dist-info/WHEEL
morgen_example_2-0.0.0.dist-info/top_level.txt
morgen_example_2-0.0.0.dist-info/RECORD
